{
  "host": "localhost",
  "port": 3030,
  "public": "./public/",
  "origins": [
    "http://localhost:3030"
  ],
  "paginate": {
    "default": 10,
    "max": 50
  },
  "sqlite": {
    "client": "sqlite3",
    "connection": "server.sqlite",
    "useNullAsDefault": true
  },
  "authentication": {
    "entity": "user",
    "service": "users",
    "secret": "tPDiut9EeZWYCm95vw8PSXY+311b3I14",
    "authStrategies": [
      "jwt",
      "local"
    ],
    "jwtOptions": {
      "header": {
        "typ": "access"
      },
      "audience": "https://yourdomain.com",
      "algorithm": "HS256",
      "expiresIn": "1d"
    },
    "local": {
      "usernameField": "email",
      "passwordField": "password"
    },
    "oauth": {
      "google": {
        "key": "<Client ID>",
        "secret": "<Client secret>"
      }
    }
  }
}